pydbt/__init__.py
pydbt/constants.py
pydbt/logger.py
pydbt/main.py
pydbt/types.py
pydbt/config/__init__.py
pydbt/handlers/__init__.py
pydbt/handlers/alert.py
pydbt/handlers/monitor.py
pydbt/handlers/alerting/__init__.py
pydbt/handlers/alerting/base.py
pydbt/handlers/alerting/dummy.py
pydbt/handlers/alerting/slack.py
pydbt/handlers/monitors/__init__.py
pydbt/handlers/monitors/base.py
pydbt/handlers/monitors/ddatadog.py
pydbt/handlers/monitors/dummy.py
pydbt/handlers/monitors/prometheus.py
pydbt/parsers/__init__.py
pydbt/parsers/formatter.py
pydbt/parsers/node.py
pydbt/utils/__init__.py
pydbt/utils/http.py
pydbt/utils/tools.py
pydbt-0.7.0.data/scripts/pydbt
tests/__init__.py
tests/fixture_loader.py
tests/test_logger.py
pydbt-0.7.0.dist-info/METADATA
pydbt-0.7.0.dist-info/WHEEL
pydbt-0.7.0.dist-info/top_level.txt
pydbt-0.7.0.dist-info/RECORD
